
{"items":[{"name":"VsGlobal","href":"VsGlobal.html","topicHref":"VsGlobal.html","topicUid":"VsGlobal","items":[{"name":"Config","href":"VsGlobal.Config.html","topicHref":"VsGlobal.Config.html","topicUid":"VsGlobal.Config"},{"name":"Events","href":"VsGlobal.Events.html","topicHref":"VsGlobal.Events.html","topicUid":"VsGlobal.Events"},{"name":"Network","href":"VsGlobal.Network.html","topicHref":"VsGlobal.Network.html","topicUid":"VsGlobal.Network"}]},{"name":"VsGlobal.AuthToken","href":"VsGlobal.AuthToken.html","topicHref":"VsGlobal.AuthToken.html","topicUid":"VsGlobal.AuthToken","items":[{"name":"Config","href":"VsGlobal.AuthToken.Config.html","topicHref":"VsGlobal.AuthToken.Config.html","topicUid":"VsGlobal.AuthToken.Config"}]},{"name":"VsGlobal.EventArguments","href":"VsGlobal.EventArguments.html","topicHref":"VsGlobal.EventArguments.html","topicUid":"VsGlobal.EventArguments","items":[{"name":"OnClientReadyEventArgs","href":"VsGlobal.EventArguments.OnClientReadyEventArgs.html","topicHref":"VsGlobal.EventArguments.OnClientReadyEventArgs.html","topicUid":"VsGlobal.EventArguments.OnClientReadyEventArgs"},{"name":"OnConnectEventArgs","href":"VsGlobal.EventArguments.OnConnectEventArgs.html","topicHref":"VsGlobal.EventArguments.OnConnectEventArgs.html","topicUid":"VsGlobal.EventArguments.OnConnectEventArgs"},{"name":"OnDisconnectEventArgs","href":"VsGlobal.EventArguments.OnDisconnectEventArgs.html","topicHref":"VsGlobal.EventArguments.OnDisconnectEventArgs.html","topicUid":"VsGlobal.EventArguments.OnDisconnectEventArgs"},{"name":"OnPayloadReceivedEventArgs","href":"VsGlobal.EventArguments.OnPayloadReceivedEventArgs.html","topicHref":"VsGlobal.EventArguments.OnPayloadReceivedEventArgs.html","topicUid":"VsGlobal.EventArguments.OnPayloadReceivedEventArgs"},{"name":"OnReconnectEventArgs","href":"VsGlobal.EventArguments.OnReconnectEventArgs.html","topicHref":"VsGlobal.EventArguments.OnReconnectEventArgs.html","topicUid":"VsGlobal.EventArguments.OnReconnectEventArgs"}]},{"name":"VsGlobal.Handlers","href":"VsGlobal.Handlers.html","topicHref":"VsGlobal.Handlers.html","topicUid":"VsGlobal.Handlers","items":[{"name":"OnClientReadyHandler","href":"VsGlobal.Handlers.OnClientReadyHandler.html","topicHref":"VsGlobal.Handlers.OnClientReadyHandler.html","topicUid":"VsGlobal.Handlers.OnClientReadyHandler"},{"name":"OnConnectHandler","href":"VsGlobal.Handlers.OnConnectHandler.html","topicHref":"VsGlobal.Handlers.OnConnectHandler.html","topicUid":"VsGlobal.Handlers.OnConnectHandler"},{"name":"OnDisconnectHandler","href":"VsGlobal.Handlers.OnDisconnectHandler.html","topicHref":"VsGlobal.Handlers.OnDisconnectHandler.html","topicUid":"VsGlobal.Handlers.OnDisconnectHandler"},{"name":"OnPayloadReceivedHandler","href":"VsGlobal.Handlers.OnPayloadReceivedHandler.html","topicHref":"VsGlobal.Handlers.OnPayloadReceivedHandler.html","topicUid":"VsGlobal.Handlers.OnPayloadReceivedHandler"},{"name":"OnReconnectHandler","href":"VsGlobal.Handlers.OnReconnectHandler.html","topicHref":"VsGlobal.Handlers.OnReconnectHandler.html","topicUid":"VsGlobal.Handlers.OnReconnectHandler"}]},{"name":"VsGlobal.Proto","href":"VsGlobal.Proto.html","topicHref":"VsGlobal.Proto.html","topicUid":"VsGlobal.Proto","items":[{"name":"Payload","href":"VsGlobal.Proto.Payload.html","topicHref":"VsGlobal.Proto.Payload.html","topicUid":"VsGlobal.Proto.Payload"},{"name":"PayloadExtensionMethods","href":"VsGlobal.Proto.PayloadExtensionMethods.html","topicHref":"VsGlobal.Proto.PayloadExtensionMethods.html","topicUid":"VsGlobal.Proto.PayloadExtensionMethods"}]}],"memberLayout":"SamePage","pdf":true}
